whichfile/__init__.py
whichfile/__main__.py
hichFile-1.0.3.dist-info/METADATA
hichFile-1.0.3.dist-info/WHEEL
hichFile-1.0.3.dist-info/entry_points.txt
hichFile-1.0.3.dist-info/top_level.txt
hichFile-1.0.3.dist-info/RECORD
