Metadata-Version: 2.1
Name: hichFile
Version: 1.0.3
Summary: Reports symlink targets and file types, like `which` and `file`.
Home-page: https://github.com/welbornprod/whichfile
Author: Christopher Welborn
Author-email: cjwelborn@live.com
License: UNKNOWN
Keywords: python python3 2 3 which file whichfile tool executable
Platform: UNKNOWN
Classifier: License :: OSI Approved :: GNU General Public License v2 or later (GPLv2+)
Classifier: Operating System :: POSIX :: Linux
Classifier: Programming Language :: Python
Classifier: Programming Language :: Python :: 3 :: Only
Requires-Dist: colr (>=0.9.1)
Requires-Dist: docopt (>=0.6.2)
Requires-Dist: findfunc (>=0.4.5)
Requires-Dist: formatblock (>=0.3.6)
Requires-Dist: python-magic (>=0.4.15)
